rostop/__init__.py
rostop/__main__.py
rostop/app.py
rostop/cli.py
rostop/ros_utils/__init__.py
rostop/ros_utils/message_formatter.py
rostop/ros_utils/subscription_manager.py
rostop/views/__init__.py
rostop/views/base_view.py
rostop/views/optimized_display.py
rostop/views/topic_display_view.py
rostop/views/topic_select_view.py
rostop-0.1.0.dist-info/METADATA
rostop-0.1.0.dist-info/WHEEL
rostop-0.1.0.dist-info/entry_points.txt
rostop-0.1.0.dist-info/top_level.txt
rostop-0.1.0.dist-info/RECORD
