Metadata-Version: 2.1
Name: rostop
Version: 0.1.0
Summary: A modern, interactive TUI for monitoring ROS topics.
Home-page: https://github.com/ZhangZiyu1216/rostop
Author: zzy
Author-email: zhangziyu_1216@qq.com
License: MIT License
Classifier: Development Status :: 3 - Alpha
Classifier: Environment :: Console :: Curses
Classifier: Intended Audience :: Developers
Classifier: License :: OSI Approved :: MIT License
Classifier: Operating System :: POSIX :: Linux
Classifier: Programming Language :: Python :: 3
Classifier: Programming Language :: Python :: 3.8
Classifier: Programming Language :: Python :: 3.9
Classifier: Programming Language :: Python :: 3.10
Classifier: Programming Language :: Python :: 3.11
Classifier: Topic :: Scientific/Engineering
Classifier: Topic :: System :: Monitoring
Requires-Python: >=3.8
Requires-Dist: pyyaml
Requires-Dist: rospy-message-converter
